sb_opentelemetry_sdk_extension_statsd/__init__.py
sb_opentelemetry_sdk_extension_statsd/version.py
sb_opentelemetry_sdk_extension_statsd-1.0.2.dist-info/WHEEL
sb_opentelemetry_sdk_extension_statsd-1.0.2.dist-info/METADATA
sb_opentelemetry_sdk_extension_statsd-1.0.2.dist-info/RECORD
