Metadata-Version: 2.3
Name: sb-opentelemetry-sdk-extension-statsd
Version: 1.0.2
Summary: StatsD extension for OpenTelemetry
Author: Rangel Reale, Rangel Reale
Author-email: Rangel Reale <rangelreale@gmail.com>, Rangel Reale <rangelspam@gmail.com>
License: Apache-2.0
Classifier: Programming Language :: Python :: 3
Classifier: License :: OSI Approved :: Apache Software License
Classifier: Operating System :: OS Independent
Classifier: Development Status :: 4 - Beta
Classifier: Intended Audience :: Developers
Classifier: Programming Language :: Python
Classifier: Programming Language :: Python :: 3.10
Classifier: Programming Language :: Python :: 3.8
Classifier: Programming Language :: Python :: 3.9
Requires-Dist: setuptools>=80.9.0
Requires-Dist: opentelemetry-sdk~=1.38
Requires-Dist: statsd-python~=0.6
Requires-Python: >=3.9
Project-URL: Bug Tracker, https://github.com/SibrosTech/otel-statsd/issues
Project-URL: Homepage, https://github.com/SibrosTech/otel-statsd/tree/master/python/opentelemetry-sdk-extension-statsd
Provides-Extra: test
